phpypam/__init__.py
phpypam/core/__init__.py
phpypam/core/api.py
phpypam/core/exceptions.py
tests/__init__.py
tests/conftest.py
phpypam-1.0.2.dist-info/LICENSE
phpypam-1.0.2.dist-info/METADATA
phpypam-1.0.2.dist-info/WHEEL
phpypam-1.0.2.dist-info/top_level.txt
phpypam-1.0.2.dist-info/RECORD
