Metadata-Version: 2.1
Name: phpypam
Version: 1.0.2
Summary: Python API client library for phpIPAM installation
Home-page: https://codeaffen.org/projects/phpypam/
Author: Christian Meißner
Author-email: Christian Meißner <cme+codeaffen@meissner.sh>
License: GPLv3
Keywords: api phpipam
Platform: UNKNOWN
Classifier: License :: OSI Approved :: GNU General Public License v3 (GPLv3)
Classifier: Programming Language :: Python :: 3
Classifier: Intended Audience :: Developers
Requires-Python: >=3.6
Requires-Dist: requests (<3.0,>=2.21)
